README.md
setup.cfg
setup.py
examples/__init__.py
examples/example.py
examples/gbm.py
examples/horovod_torch.py
examples/hyperband.py
examples/hyperbelt.py
examples/skopt_torch.py
hyperspace/__init__.py
hyperspace/benchmarks.py
hyperspace/hyperdrive/__init__.py
hyperspace/hyperdrive/hyperbelt/__init__.py
hyperspace/hyperdrive/hyperbelt/hyperband.py
hyperspace/hyperdrive/hyperbelt/hyperbelt.py
hyperspace/hyperdrive/skopt/__init__.py
hyperspace/hyperdrive/skopt/dualdrive.py
hyperspace/hyperdrive/skopt/hyperdrive.py
hyperspace/hyperdrive/skopt/models.py
hyperspace/kepler/__init__.py
hyperspace/kepler/data_utils.py
hyperspace/kepler/plots.py
hyperspace/rover/__init__.py
hyperspace/rover/checkpoints.py
hyperspace/rover/latin_hypercube_sampler.py
hyperspace/space/__init__.py
hyperspace/space/skopt/__init__.py
hyperspace/space/skopt/mapping_space.py
hyperspace/space/skopt/space.py
hyperspace/tests/__init__.py
hyperspace/tests/test_mapping_space.py
hyperspace/tests/test_space.py
hyperspaces.egg-info/PKG-INFO
hyperspaces.egg-info/SOURCES.txt
hyperspaces.egg-info/dependency_links.txt
hyperspaces.egg-info/requires.txt
hyperspaces.egg-info/top_level.txt