Metadata-Version: 1.2
Name: hyperspaces
Version: 0.4.0
Summary: Distributed Bayesian model-based optimization
Home-page: https://github.com/yngtodd/hyperspace
Author: Todd Young
Author-email: youngmt1@ornl.gov
License: MIT
Keywords: parallel optimization smbo
Platform: UNKNOWN
Requires-Python: >=3.6
